alma/__init__.py
alma/benchmark_model.py
alma/arguments/__init__.py
alma/arguments/benchmark_args.py
alma/benchmark/__init__.py
alma/benchmark/benchmark.py
alma/benchmark/benchmark_config.py
alma/benchmark/log.py
alma/benchmark/warmup.py
alma/conversions/__init__.py
alma/conversions/conversion_options.py
alma/conversions/select.py
alma/conversions/options/__init__.py
alma/conversions/options/bf16.py
alma/conversions/options/compile.py
alma/conversions/options/export_aotinductor.py
alma/conversions/options/export_compile.py
alma/conversions/options/export_eager.py
alma/conversions/options/export_quant.py
alma/conversions/options/fake_quant.py
alma/conversions/options/fp16.py
alma/conversions/options/jit_trace.py
alma/conversions/options/onnx.py
alma/conversions/options/optimum_quanto.py
alma/conversions/options/quant_edge_convert.py
alma/conversions/options/torchao_autoquant.py
alma/conversions/options/torchao_quant.py
alma/conversions/options/torchscript.py
alma/conversions/options/utils/__init__.py
alma/conversions/options/utils/compile_settings.py
alma/conversions/options/utils/export.py
alma/conversions/options/utils/qconfigs.py
alma/conversions/options/utils/checks/__init__.py
alma/conversions/options/utils/checks/imports.py
alma/conversions/options/utils/checks/type.py
alma/dataloader/__init__.py
alma/dataloader/create.py
alma/dataloader/dataloader.py
alma/quantization/PTQ.py
alma/quantization/QAT.py
alma/quantization/__init__.py
alma/quantization/utils.py
alma/utils/__init__.py
alma/utils/data.py
alma/utils/device.py
alma/utils/ipdb_hook.py
alma/utils/load_model.py
alma/utils/setup_logging.py
alma/utils/times.py
alma/utils/checks/__init__.py
alma/utils/checks/all.py
alma/utils/checks/config.py
alma/utils/checks/data.py
alma/utils/checks/inputs.py
alma/utils/checks/model.py
alma/utils/multiprocessing/__init__.py
alma/utils/multiprocessing/error_handling.py
alma/utils/multiprocessing/multiprocessing.py
alma/utils/multiprocessing/traceback.py
alma_torch-0.3.7.dist-info/LICENSE
alma_torch-0.3.7.dist-info/METADATA
alma_torch-0.3.7.dist-info/WHEEL
alma_torch-0.3.7.dist-info/top_level.txt
alma_torch-0.3.7.dist-info/RECORD
