Metadata-Version: 2.2
Name: alma-torch
Version: 0.3.7
Summary: A package for benchmarking the speed of different PyTorch conversion options
Author-email: Saif Haq <saif.haq99@gmail.com>, Oscar Savolainen <oscar.savolainen@hotmail.com>
Project-URL: Homepage, https://github.com/saifhaq/alma
Project-URL: Issues, https://github.com/saifhaq/alma/issues
Classifier: Programming Language :: Python :: 3
Classifier: License :: OSI Approved :: MIT License
Classifier: Operating System :: OS Independent
Requires-Python: >=3.8
License-File: LICENSE
